examples/01_basic.py
examples/02_advanced.py
examples/03_professional.py
examples/04_real_world.py
examples/05_websocket.py
examples/06_browser_config.py
examples/07_hooks_and_interactions.py
examples/README.md
patchright_httpx/__init__.py
patchright_httpx/_async_client.py
patchright_httpx/_client.py
patchright_httpx/_config.py
patchright_httpx/_models.py
patchright_httpx/_tools.py
patchright_httpx/_types.py
patchright_httpx/_utils.py
patchright_httpx/_websocket.py
patchright_httpx-0.1.1.dist-info/licenses/LICENSE
patchright_httpx-0.1.1.dist-info/METADATA
patchright_httpx-0.1.1.dist-info/WHEEL
patchright_httpx-0.1.1.dist-info/top_level.txt
patchright_httpx-0.1.1.dist-info/RECORD
