Metadata-Version: 2.4
Name: patchright-httpx
Version: 0.1.1
Summary: HTTPX-style HTTP client powered by Patchright browser automation
Home-page: https://github.com/Color_Fox/patchright-httpx
Author: Color_Fox
Author-email: 
License: MIT
Project-URL: Homepage, https://github.com/Color_Fox/patchright-httpx
Project-URL: Documentation, https://github.com/Color_Fox/patchright-httpx/blob/main/README.md
Project-URL: Repository, https://github.com/Color_Fox/patchright-httpx
Project-URL: Bug Tracker, https://github.com/Color_Fox/patchright-httpx/issues
Project-URL: Changelog, https://github.com/Color_Fox/patchright-httpx/blob/main/CHANGELOG.md
Keywords: http,httpx,requests,browser,playwright,patchright,automation,websocket,crawler,scraping
Classifier: Development Status :: 3 - Alpha
Classifier: Intended Audience :: Developers
Classifier: Topic :: Software Development :: Libraries :: Python Modules
Classifier: Topic :: Internet :: WWW/HTTP
Classifier: Topic :: Internet :: WWW/HTTP :: Browsers
Classifier: Topic :: Software Development :: Testing
Classifier: License :: OSI Approved :: MIT License
Classifier: Programming Language :: Python :: 3
Classifier: Programming Language :: Python :: 3.8
Classifier: Programming Language :: Python :: 3.9
Classifier: Programming Language :: Python :: 3.10
Classifier: Programming Language :: Python :: 3.11
Classifier: Programming Language :: Python :: 3.12
Classifier: Operating System :: OS Independent
Requires-Python: >=3.8
License-File: LICENSE
Requires-Dist: patchright>=1.0.0
Dynamic: home-page
Dynamic: license-file
Dynamic: requires-python
